multimodalsim_viewer/__init__.py
multimodalsim_viewer/common/__init__.py
multimodalsim_viewer/common/utils.py
multimodalsim_viewer/common/environments/.env
multimodalsim_viewer/models/__init__.py
multimodalsim_viewer/models/environment.py
multimodalsim_viewer/models/leg.py
multimodalsim_viewer/models/passenger.py
multimodalsim_viewer/models/serializable.py
multimodalsim_viewer/models/simulation_information.py
multimodalsim_viewer/models/state.py
multimodalsim_viewer/models/stop.py
multimodalsim_viewer/models/update.py
multimodalsim_viewer/models/vehicle.py
multimodalsim_viewer/server/__init__.py
multimodalsim_viewer/server/data_collector.py
multimodalsim_viewer/server/data_manager.py
multimodalsim_viewer/server/http_routes.py
multimodalsim_viewer/server/log_manager.py
multimodalsim_viewer/server/scripts.py
multimodalsim_viewer/server/server.py
multimodalsim_viewer/server/simulation.py
multimodalsim_viewer/server/simulation_manager.py
multimodalsim_viewer/ui/__init__.py
multimodalsim_viewer/ui/angular_app.py
multimodalsim_viewer/ui/static/chunk-IILFIRWZ.js
multimodalsim_viewer/ui/static/chunk-L2ZL6Q4W.js
multimodalsim_viewer/ui/static/environment.json
multimodalsim_viewer/ui/static/favicon.ico
multimodalsim_viewer/ui/static/index.html
multimodalsim_viewer/ui/static/main-XYH7FCFC.js
multimodalsim_viewer/ui/static/polyfills-FFHMD2TL.js
multimodalsim_viewer/ui/static/styles-2KWGWV5P.css
multimodalsim_viewer/ui/static/bitmap-fonts/custom-sans-serif.png
multimodalsim_viewer/ui/static/bitmap-fonts/custom-sans-serif.xml
multimodalsim_viewer/ui/static/images/control-bar.png
multimodalsim_viewer/ui/static/images/passenger.png
multimodalsim_viewer/ui/static/images/simulation-control-bar.png
multimodalsim_viewer/ui/static/images/stop.png
multimodalsim_viewer/ui/static/images/undefined-texture.png
multimodalsim_viewer/ui/static/images/vehicle.png
multimodalsim_viewer/ui/static/images/zoomed-out-passenger.png
multimodalsim_viewer/ui/static/images/zoomed-out-stop.png
multimodalsim_viewer-0.1.4.0.dist-info/METADATA
multimodalsim_viewer-0.1.4.0.dist-info/WHEEL
multimodalsim_viewer-0.1.4.0.dist-info/entry_points.txt
multimodalsim_viewer-0.1.4.0.dist-info/top_level.txt
multimodalsim_viewer-0.1.4.0.dist-info/RECORD
