Metadata-Version: 2.4
Name: multimodalsim_viewer
Version: 0.1.4.0
Summary: Multimodal simulation viewer
Keywords: flask angular ui multimodal server
Requires-Python: >=3.10
Requires-Dist: flask==3.1.1
Requires-Dist: flask-socketio==5.5.1
Requires-Dist: eventlet==0.40.0
Requires-Dist: websocket-client==1.8.0
Requires-Dist: filelock==3.18.0
Requires-Dist: flask_cors==6.0.0
Requires-Dist: questionary==2.1.0
Requires-Dist: python-dotenv==1.1.0
Requires-Dist: multimodalsim==0.0.1
Requires-Dist: get_latest_version==1.0.3
Requires-Dist: setuptools==80.9.0
Provides-Extra: dev
Requires-Dist: black==25.1.0; extra == "dev"
Requires-Dist: pylint==3.3.7; extra == "dev"
Requires-Dist: isort==6.0.1; extra == "dev"
Provides-Extra: build
Requires-Dist: build; extra == "build"
Requires-Dist: twine; extra == "build"
Dynamic: description
Dynamic: description-content-type
Dynamic: keywords
Dynamic: provides-extra
Dynamic: requires-dist
Dynamic: requires-python
Dynamic: summary
